just_prompt_it-1.0.1.dist-info/licenses/LICENSE
prompt_studio/__init__.py
prompt_studio/exceptions.py
prompt_studio/prompt_studio.py
prompt_studio/render.py
just_prompt_it-1.0.1.dist-info/METADATA
just_prompt_it-1.0.1.dist-info/WHEEL
just_prompt_it-1.0.1.dist-info/top_level.txt
just_prompt_it-1.0.1.dist-info/RECORD
