Metadata-Version: 2.4
Name: just-prompt-it
Version: 1.0.1
Summary: A Python SDK for fetching and rendering prompts from Prompt Studio API
Author-email: Trustsoft <contact@trustsoft.com.vn>
Project-URL: Homepage, https://github.com/trustsoftvn/prompt_studio_sdk
Project-URL: Repository, https://github.com/trustsoftvn/prompt_studio_sdk.git
Project-URL: Documentation, https://github.com/trustsoftvn/prompt_studio_sdk#readme
Project-URL: Issues, https://github.com/trustsoftvn/prompt_studio_sdk/issues
Keywords: prompt,template,api,sdk,jinja2
Classifier: Development Status :: 3 - Alpha
Classifier: Intended Audience :: Developers
Classifier: Programming Language :: Python :: 3
Classifier: Programming Language :: Python :: 3.8
Classifier: Programming Language :: Python :: 3.9
Classifier: Programming Language :: Python :: 3.10
Classifier: Programming Language :: Python :: 3.11
Classifier: Programming Language :: Python :: 3.12
Classifier: License :: OSI Approved :: MIT License
Classifier: Operating System :: OS Independent
Requires-Python: >=3.8.1
License-File: LICENSE
Requires-Dist: httpx>=0.24.0
Requires-Dist: jinja2>=3.0.0
Provides-Extra: dev
Requires-Dist: pytest>=7.0.0; extra == "dev"
Requires-Dist: pytest-cov>=4.0.0; extra == "dev"
Requires-Dist: pytest-httpx>=0.21.0; extra == "dev"
Requires-Dist: pytest-asyncio>=0.21.0; extra == "dev"
Requires-Dist: black>=23.0.0; extra == "dev"
Requires-Dist: isort>=5.12.0; extra == "dev"
Requires-Dist: flake8>=6.0.0; extra == "dev"
Requires-Dist: mypy>=1.0.0; extra == "dev"
Dynamic: license-file
